libcloudforensics/__init__.py
libcloudforensics/errors.py
libcloudforensics/logging_utils.py
libcloudforensics/prompts.py
libcloudforensics/providers/__init__.py
libcloudforensics/providers/aws/__init__.py
libcloudforensics/providers/aws/forensics.py
libcloudforensics/providers/aws/internal/__init__.py
libcloudforensics/providers/aws/internal/account.py
libcloudforensics/providers/aws/internal/common.py
libcloudforensics/providers/aws/internal/ebs.py
libcloudforensics/providers/aws/internal/ec2.py
libcloudforensics/providers/aws/internal/iam.py
libcloudforensics/providers/aws/internal/iampolicies/ebs_copy_to_s3_policy.json
libcloudforensics/providers/aws/internal/iampolicies/ec2_assume_role_policy.json
libcloudforensics/providers/aws/internal/iampolicies/revoke_old_sessions.json
libcloudforensics/providers/aws/internal/kms.py
libcloudforensics/providers/aws/internal/log.py
libcloudforensics/providers/aws/internal/s3.py
libcloudforensics/providers/azure/__init__.py
libcloudforensics/providers/azure/forensics.py
libcloudforensics/providers/azure/internal/__init__.py
libcloudforensics/providers/azure/internal/account.py
libcloudforensics/providers/azure/internal/common.py
libcloudforensics/providers/azure/internal/compute.py
libcloudforensics/providers/azure/internal/compute_base_resource.py
libcloudforensics/providers/azure/internal/monitoring.py
libcloudforensics/providers/azure/internal/network.py
libcloudforensics/providers/azure/internal/resource.py
libcloudforensics/providers/azure/internal/storage.py
libcloudforensics/providers/gcp/__init__.py
libcloudforensics/providers/gcp/forensics.py
libcloudforensics/providers/gcp/internal/__init__.py
libcloudforensics/providers/gcp/internal/bigquery.py
libcloudforensics/providers/gcp/internal/build.py
libcloudforensics/providers/gcp/internal/cloudresourcemanager.py
libcloudforensics/providers/gcp/internal/cloudsql.py
libcloudforensics/providers/gcp/internal/common.py
libcloudforensics/providers/gcp/internal/compute.py
libcloudforensics-20250721.dist-info/LICENSE
libcloudforensics-20250721.dist-info/METADATA
libcloudforensics-20250721.dist-info/WHEEL
libcloudforensics-20250721.dist-info/entry_points.txt
libcloudforensics-20250721.dist-info/RECORD
